Workbook

Sheet Export Summary
B3: This document was exported from Numbers. Each table was converted to an Excel worksheet. All other objects on each Numbers sheet were placed on separate worksheets. Please be aware that formula calculations may differ in Excel.
B7: Numbers Sheet Name | C7: Numbers Table Name | D7: Excel Worksheet Name
B9: Assumptions
C10: Table 1 | D10: Assumptions
B11: Monthly P&L
C12: Table 1 | D12: Monthly P&L
B13: Sensitivity Analysis
C14: Table 1 | D14: Sensitivity Analysis
B15: Summary Dashboard
C16: Table 1 | D16: Summary Dashboard

Sheet Assumptions
A1: KIDBOOK CREATOR - P&L FORECASTING MODEL
A2: Version 2.0 | Last Updated: 2026-01-29
A4: FIXED MONTHLY COSTS
A5: Supabase Pro | B5: 25
A6: Netlify | B6: 9
A7: Buffer for Additional Services | B7: 100
A8: TOTAL FIXED MONTHLY | B8: 134
A10: ONE-TIME SETUP COSTS
A11: Gemini API Credits | B11: 150
A12: Domain Registration | B12: 100
A13: Example Books Creation | B13: 75
A14: Friends & Family Testing | B14: 350
A15: TOTAL SETUP COSTS | B15: 675
A17: PRICING
A18: Digital Book (PDF) | B18: 15
A19: Printed Hardcover Book | B19: 45
A21: CONVERSION FUNNEL (EDITABLE)
A22: Preview → Digital Conversion | B22: 0.03 | C22: ← Edit this
A23: Preview → Printed Conversion | B23: 0.03 | C23: ← Edit this
A25: VARIABLE COSTS - PREVIEW
A26: AI Generation (1 image + text) | B26: 0.09
A28: VARIABLE COSTS - DIGITAL BOOK
A29: AI Generation | B29: 0.5
A30: Storage (permanent) | B30: 0.02
A31: Payment Processing (2.9% + $0.30) | B31: 0.74
A32: TOTAL COST PER DIGITAL | B32: 1.26
A34: VARIABLE COSTS - PRINTED HARDCOVER
A35: AI Generation | B35: 0.5
A36: Storage (permanent) | B36: 0.02
A37: Printing (Lulu - 24 pages) | B37: 14.5
A38: Shipping (EU average) | B38: 12
A39: Payment Processing (2.9% + $0.30) | B39: 1.61
A40: TOTAL COST PER PRINTED | B40: 28.63

Sheet Monthly P&L
A1: KIDBOOK CREATOR - 12 MONTH P&L PROJECTION
A3: MONTH | B3: Jan | C3: Feb | D3: Mar | E3: Apr | F3: May | G3: Jun | H3: Jul | I3: Aug | J3: Sep | K3: Oct | L3: Nov | M3: Dec | N3: TOTAL
A5: VOLUME METRICS (EDITABLE)
A6: Preview Generations | B6: 300 | C6: =B6*1.2 -> 360 | D6: =C6*1.2 -> 432 | E6: =D6*1.2 -> 518.4 | F6: =E6*1.2 -> 622.08 | G6: =F6*1.2 -> 746.496 | H6: =G6*1.2 -> 895.7952 | I6: =H6*1.2 -> 1074.9542 | J6: =I6*1.2 -> 1289.9451 | ... M6: =L6*1.2 -> 2229.0251 | N6: =SUM(B6:M6) -> 11874.151
A7: Digital Conversions (2%) | B7: =B6*'Assumptions'!$B$22 -> 9 | C7: =C6*'Assumptions'!$B$22 -> 10.8 | D7: =D6*'Assumptions'!$B$22 -> 12.96 | E7: =E6*'Assumptions'!$B$22 -> 15.552 | F7: =F6*'Assumptions'!$B$22 -> 18.6624 | G7: =G6*'Assumptions'!$B$22 -> 22.39488 | H7: =H6*'Assumptions'!$B$22 -> 26.873856 | I7: =I6*'Assumptions'!$B$22 -> 32.248627 | ... M7: =M6*'Assumptions'!$B$22 -> 66.870753 | N7: =SUM(B7:M7) -> 356.22452
A8: Printed Conversions (2%) | B8: =B6*'Assumptions'!$B$23 -> 9 | C8: =C6*'Assumptions'!$B$23 -> 10.8 | D8: =D6*'Assumptions'!$B$23 -> 12.96 | E8: =E6*'Assumptions'!$B$23 -> 15.552 | F8: =F6*'Assumptions'!$B$23 -> 18.6624 | G8: =G6*'Assumptions'!$B$23 -> 22.39488 | H8: =H6*'Assumptions'!$B$23 -> 26.873856 | I8: =I6*'Assumptions'!$B$23 -> 32.248627 | ... M8: =M6*'Assumptions'!$B$23 -> 66.870753 | N8: =SUM(B8:M8) -> 356.22452
A10: REVENUE
A11: Digital Books ($15 each) | B11: =B7*'Assumptions'!$B$18 -> 135 | C11: =C7*'Assumptions'!$B$18 -> 162 | D11: =D7*'Assumptions'!$B$18 -> 194.4 | E11: =E7*'Assumptions'!$B$18 -> 233.28 | F11: =F7*'Assumptions'!$B$18 -> 279.936 | G11: =G7*'Assumptions'!$B$18 -> 335.9232 | H11: =H7*'Assumptions'!$B$18 -> 403.10784 | I11: =I7*'Assumptions'!$B$18 -> 483.72941 | ... M11: =M7*'Assumptions'!$B$18 -> 1003.0613 | N11: =SUM(B11:M11) -> 5343.3678
A12: Printed Books ($45 each) | B12: =B8*'Assumptions'!$B$19 -> 405 | C12: =C8*'Assumptions'!$B$19 -> 486 | D12: =D8*'Assumptions'!$B$19 -> 583.2 | E12: =E8*'Assumptions'!$B$19 -> 699.84 | F12: =F8*'Assumptions'!$B$19 -> 839.808 | G12: =G8*'Assumptions'!$B$19 -> 1007.7696 | H12: =H8*'Assumptions'!$B$19 -> 1209.3235 | I12: =I8*'Assumptions'!$B$19 -> 1451.1882 | ... M12: =M8*'Assumptions'!$B$19 -> 3009.1839 | N12: =SUM(B12:M12) -> 16030.103
A13: TOTAL REVENUE | B13: =B11+B12 -> 540 | C13: =C11+C12 -> 648 | D13: =D11+D12 -> 777.6 | E13: =E11+E12 -> 933.12 | F13: =F11+F12 -> 1119.744 | G13: =G11+G12 -> 1343.6928 | H13: =H11+H12 -> 1612.4314 | I13: =I11+I12 -> 1934.9176 | ... M13: =M11+M12 -> 4012.2452 | N13: =SUM(B13:M13) -> 21373.471
A15: VARIABLE COSTS
A16: Preview Generation Costs | B16: =B6*'Assumptions'!$B$26 -> 27 | C16: =C6*'Assumptions'!$B$26 -> 32.4 | D16: =D6*'Assumptions'!$B$26 -> 38.88 | E16: =E6*'Assumptions'!$B$26 -> 46.656 | F16: =F6*'Assumptions'!$B$26 -> 55.9872 | G16: =G6*'Assumptions'!$B$26 -> 67.18464 | H16: =H6*'Assumptions'!$B$26 -> 80.621568 | I16: =I6*'Assumptions'!$B$26 -> 96.745882 | ... M16: =M6*'Assumptions'!$B$26 -> 200.61226 | N16: =SUM(B16:M16) -> 1068.6736
A17: Digital Book Costs | B17: =B7*'Assumptions'!$B$32 -> 11.34 | C17: =C7*'Assumptions'!$B$32 -> 13.608 | D17: =D7*'Assumptions'!$B$32 -> 16.3296 | E17: =E7*'Assumptions'!$B$32 -> 19.59552 | F17: =F7*'Assumptions'!$B$32 -> 23.514624 | G17: =G7*'Assumptions'!$B$32 -> 28.217549 | H17: =H7*'Assumptions'!$B$32 -> 33.861059 | I17: =I7*'Assumptions'!$B$32 -> 40.63327 | ... M17: =M7*'Assumptions'!$B$32 -> 84.257149 | N17: =SUM(B17:M17) -> 448.8429
A18: Printed Book Costs | B18: =B8*'Assumptions'!$B$40 -> 257.67 | C18: =C8*'Assumptions'!$B$40 -> 309.204 | D18: =D8*'Assumptions'!$B$40 -> 371.0448 | E18: =E8*'Assumptions'!$B$40 -> 445.25376 | F18: =F8*'Assumptions'!$B$40 -> 534.30451 | G18: =G8*'Assumptions'!$B$40 -> 641.16541 | H18: =H8*'Assumptions'!$B$40 -> 769.3985 | I18: =I8*'Assumptions'!$B$40 -> 923.2782 | ... M18: =M8*'Assumptions'!$B$40 -> 1914.5097 | N18: =SUM(B18:M18) -> 10198.708
A19: Refunds (3% of revenue) | B19: =B13*0.03 -> 16.2 | C19: =C13*0.03 -> 19.44 | D19: =D13*0.03 -> 23.328 | E19: =E13*0.03 -> 27.9936 | F19: =F13*0.03 -> 33.59232 | G19: =G13*0.03 -> 40.310784 | H19: =H13*0.03 -> 48.372941 | I19: =I13*0.03 -> 58.047529 | ... M19: =M13*0.03 -> 120.36736 | N19: =SUM(B19:M19) -> 641.20414
A20: Failed Prints (1.5%) | B20: =B8*'Assumptions'!$B$40*0.015 -> 3.86505 | C20: =C8*'Assumptions'!$B$40*0.015 -> 4.63806 | D20: =D8*'Assumptions'!$B$40*0.015 -> 5.565672 | E20: =E8*'Assumptions'!$B$40*0.015 -> 6.6788064 | F20: =F8*'Assumptions'!$B$40*0.015 -> 8.0145677 | G20: =G8*'Assumptions'!$B$40*0.015 -> 9.6174812 | H20: =H8*'Assumptions'!$B$40*0.015 -> 11.540977 | I20: =I8*'Assumptions'!$B$40*0.015 -> 13.849173 | ... M20: =M8*'Assumptions'!$B$40*0.015 -> 28.717645 | N20: =SUM(B20:M20) -> 152.98062
A21: TOTAL VARIABLE COSTS | B21: =SUM(B16:B20) -> 316.07505 | C21: =SUM(C16:C20) -> 379.29006 | D21: =SUM(D16:D20) -> 455.14807 | E21: =SUM(E16:E20) -> 546.17769 | F21: =SUM(F16:F20) -> 655.41322 | G21: =SUM(G16:G20) -> 786.49587 | H21: =SUM(H16:H20) -> 943.79504 | I21: =SUM(I16:I20) -> 1132.5541 | ... M21: =SUM(M16:M20) -> 2348.4641 | N21: =SUM(B21:M21) -> 12510.409
A23: GROSS PROFIT | B23: =B13-B21 -> 223.92495 | C23: =C13-C21 -> 268.70994 | D23: =D13-D21 -> 322.45193 | E23: =E13-E21 -> 386.94231 | F23: =F13-F21 -> 464.33078 | G23: =G13-G21 -> 557.19693 | H23: =H13-H21 -> 668.63632 | I23: =I13-I21 -> 802.36358 | ... M23: =M13-M21 -> 1663.7811 | N23: =SUM(B23:M23) -> 8863.062
A24: Gross Margin % | B24: =IF(B13>0,B23/B13,0) -> 0.41467583 | C24: =IF(C13>0,C23/C13,0) -> 0.41467583 | D24: =IF(D13>0,D23/D13,0) -> 0.41467583 | E24: =IF(E13>0,E23/E13,0) -> 0.41467583 | F24: =IF(F13>0,F23/F13,0) -> 0.41467583 | G24: =IF(G13>0,G23/G13,0) -> 0.41467583 | H24: =IF(H13>0,H23/H13,0) -> 0.41467583 | I24: =IF(I13>0,I23/I13,0) -> 0.41467583 | ... N24: =IF(N13>0,N23/N13,0) -> 0.41467583
A26: FIXED COSTS
A27: Monthly Fixed Costs | B27: ='Assumptions'!$B$9 -> 0 | C27: ='Assumptions'!$B$9 -> 0 | D27: ='Assumptions'!$B$9 -> 0 | E27: ='Assumptions'!$B$9 -> 0 | F27: ='Assumptions'!$B$9 -> 0 | G27: ='Assumptions'!$B$9 -> 0 | H27: ='Assumptions'!$B$9 -> 0 | I27: ='Assumptions'!$B$9 -> 0 | ... M27: ='Assumptions'!$B$9 -> 0 | N27: =SUM(B27:M27) -> 0
A29: NET PROFIT | B29: =B23-B27 -> 223.92495 | C29: =C23-C27 -> 268.70994 | D29: =D23-D27 -> 322.45193 | E29: =E23-E27 -> 386.94231 | F29: =F23-F27 -> 464.33078 | G29: =G23-G27 -> 557.19693 | H29: =H23-H27 -> 668.63632 | I29: =I23-I27 -> 802.36358 | ... M29: =M23-M27 -> 1663.7811 | N29: =SUM(B29:M29) -> 8863.062
A30: Net Margin % | B30: =IF(B13>0,B29/B13,0) -> 0.41467583 | C30: =IF(C13>0,C29/C13,0) -> 0.41467583 | D30: =IF(D13>0,D29/D13,0) -> 0.41467583 | E30: =IF(E13>0,E29/E13,0) -> 0.41467583 | F30: =IF(F13>0,F29/F13,0) -> 0.41467583 | G30: =IF(G13>0,G29/G13,0) -> 0.41467583 | H30: =IF(H13>0,H29/H13,0) -> 0.41467583 | I30: =IF(I13>0,I29/I13,0) -> 0.41467583 | ... N30: =IF(N13>0,N29/N13,0) -> 0.41467583

Sheet Sensitivity Analysis
A1: SENSITIVITY ANALYSIS
A3: CONVERSION RATE IMPACT
A4: (Monthly: 300 Previews)
A6: Conversion Rate | B6: 0.02 | C6: 0.03 | D6: 0.04 | E6: 0.05 | F6: 0.06
A7: Total Conversions | B7: 6 | C7: 9 | D7: 12 | E7: 15 | F7: 18
A8: Revenue | B8: 225 | C8: 337.5 | D8: 450 | E8: 562.5 | F8: 675
A9: Variable Costs | B9: 157.725 | C9: 223.0875 | D9: 288.45 | E9: 353.8125 | F9: 419.175
A10: Net Profit | B10: =B8-B9-134 -> -66.725 | C10: =C8-C9-134 -> -19.5875 | D10: =D8-D9-134 -> 27.55 | E10: =E8-E9-134 -> 74.6875 | F10: =F8-F9-134 -> 121.825
A13: PRICING IMPACT
A14: (Monthly: 300 Previews, 4% Conversion)
A16: Printed Book Price | B16: 40 | C16: 42 | D16: 45 | E16: 48 | F16: 50
A17: Total Revenue | B17: 405 | C17: 423 | D17: 450 | E17: 477 | F17: 495
A18: Net Profit | B18: =B17-288.45-134 -> -17.45 | C18: =C17-288.45-134 -> 0.55 | D18: =D17-288.45-134 -> 27.55 | E18: =E17-288.45-134 -> 54.55 | F18: =F17-288.45-134 -> 72.55

Sheet Summary Dashboard
A1: KIDBOOK CREATOR - EXECUTIVE SUMMARY
A3: KEY METRICS (Year 1)
A5: Total Preview Generations | B5: ='Monthly P&L'!N6 -> 11874.151
A6: Total Conversions | B6: ='Monthly P&L'!N7+'Monthly P&L'!N8 -> 712.44904
A8: FINANCIAL PERFORMANCE
A9: Total Revenue | B9: ='Monthly P&L'!N13 -> 21373.471
A10: Gross Profit | B10: ='Monthly P&L'!N23 -> 8863.062
A11: Net Profit | B11: ='Monthly P&L'!N29 -> 8863.062
A13: UNIT ECONOMICS
A15: Per Digital Book:
A16: Revenue | B16: 15
A17: Cost | B17: 1.26
A18: Gross Profit | B18: 13.74 | C18: 91.6%
A20: Per Printed Book:
A21: Revenue | B21: 45
A22: Cost | B22: 28.63
A23: Gross Profit | B23: 16.37 | C23: 36.4%
A25: BREAK-EVEN ANALYSIS
A26: Monthly Fixed Costs | B26: 134
A27: Previews needed per month | B27: 262
A28: Conversions needed per month | B28: 10.5
